hiscan/__init__.py
hiscan/func.py
hiscan/main.py
hiscan-0.0.5.dist-info/LICENSE
hiscan-0.0.5.dist-info/METADATA
hiscan-0.0.5.dist-info/WHEEL
hiscan-0.0.5.dist-info/entry_points.txt
hiscan-0.0.5.dist-info/top_level.txt
hiscan-0.0.5.dist-info/RECORD
